unpack_unitypackage.py
unpack_unitypackage-1.1.0.data/scripts/unpack_unitypackage.py
unpack_unitypackage-1.1.0.dist-info/LICENSE
unpack_unitypackage-1.1.0.dist-info/METADATA
unpack_unitypackage-1.1.0.dist-info/WHEEL
unpack_unitypackage-1.1.0.dist-info/entry_points.txt
unpack_unitypackage-1.1.0.dist-info/top_level.txt
unpack_unitypackage-1.1.0.dist-info/RECORD
