Metadata-Version: 2.2
Name: unpack-unitypackage
Version: 1.1.0
Summary: 解压和提取Unity包文件的工具
Author: xiayangqun
Author-email: xyq377x@gmail.com
Classifier: Programming Language :: Python :: 3
Classifier: License :: OSI Approved :: MIT License
Classifier: Operating System :: OS Independent
Requires-Python: >=3.6
License-File: LICENSE
Requires-Dist: unitypackage_extractor
Dynamic: author
Dynamic: author-email
Dynamic: classifier
Dynamic: description
Dynamic: description-content-type
Dynamic: requires-dist
Dynamic: requires-python
Dynamic: summary
